remlapreprocesspy/__init__.py
remlapreprocesspy/remlapreprocesspy.py
remlapreprocesspy-4.1.3.dist-info/LICENSE
remlapreprocesspy-4.1.3.dist-info/METADATA
remlapreprocesspy-4.1.3.dist-info/WHEEL
remlapreprocesspy-4.1.3.dist-info/RECORD
